tenforty/__init__.py
tenforty/_ots_form_models.py
tenforty/core.py
tenforty/form_resolution.py
tenforty/mappings.py
tenforty/models.py
tenforty/otslib.cpython-310-x86_64-linux-gnu.so
tenforty/backends/__init__.py
tenforty/backends/graph.py
tenforty/backends/ots.py
tenforty/backends/protocol.py
tenforty/otslib/ots.cpp
tenforty/otslib/ots.pyx
tenforty/otslib/ots_2018_CA_540.cpp
tenforty/otslib/ots_2018_CA_540.pxd
tenforty/otslib/ots_2018_MA_1.cpp
tenforty/otslib/ots_2018_MA_1.pxd
tenforty/otslib/ots_2018_NC_D400.cpp
tenforty/otslib/ots_2018_NC_D400.pxd
tenforty/otslib/ots_2018_NJ_1040.cpp
tenforty/otslib/ots_2018_NJ_1040.pxd
tenforty/otslib/ots_2018_NY_IT201.cpp
tenforty/otslib/ots_2018_NY_IT201.pxd
tenforty/otslib/ots_2018_OH_IT1040.cpp
tenforty/otslib/ots_2018_OH_IT1040.pxd
tenforty/otslib/ots_2018_PA_40.cpp
tenforty/otslib/ots_2018_PA_40.pxd
tenforty/otslib/ots_2018_US_1040.cpp
tenforty/otslib/ots_2018_US_1040.pxd
tenforty/otslib/ots_2018_US_1040_Sched_C.cpp
tenforty/otslib/ots_2018_US_1040_Sched_C.pxd
tenforty/otslib/ots_2018_VA_760.cpp
tenforty/otslib/ots_2018_VA_760.pxd
tenforty/otslib/ots_2019_CA_540.cpp
tenforty/otslib/ots_2019_CA_540.pxd
tenforty/otslib/ots_2019_MA_1.cpp
tenforty/otslib/ots_2019_MA_1.pxd
tenforty/otslib/ots_2019_NC_D400.cpp
tenforty/otslib/ots_2019_NC_D400.pxd
tenforty/otslib/ots_2019_NJ_1040.cpp
tenforty/otslib/ots_2019_NJ_1040.pxd
tenforty/otslib/ots_2019_NY_IT201.cpp
tenforty/otslib/ots_2019_NY_IT201.pxd
tenforty/otslib/ots_2019_OH_IT1040.cpp
tenforty/otslib/ots_2019_OH_IT1040.pxd
tenforty/otslib/ots_2019_PA_40.cpp
tenforty/otslib/ots_2019_PA_40.pxd
tenforty/otslib/ots_2019_US_1040.cpp
tenforty/otslib/ots_2019_US_1040.pxd
tenforty/otslib/ots_2019_US_1040_Sched_C.cpp
tenforty/otslib/ots_2019_US_1040_Sched_C.pxd
tenforty/otslib/ots_2019_VA_760.cpp
tenforty/otslib/ots_2019_VA_760.pxd
tenforty/otslib/ots_2020_CA_540.cpp
tenforty/otslib/ots_2020_CA_540.pxd
tenforty-2025.1.dist-info/METADATA
tenforty-2025.1.dist-info/WHEEL
tenforty-2025.1.dist-info/top_level.txt
tenforty-2025.1.dist-info/RECORD
tenforty-2025.1.dist-info/licenses/LICENSE.txt
