Metadata-Version: 2.4
Name: tenforty
Version: 2025.1
Summary: Library to compute US federal taxes, and state taxes for some states.
Author-email: Mike Macpherson <mmacpherson@users.noreply.github.com>
License: MIT License
Classifier: Programming Language :: Cython
Classifier: Programming Language :: Python :: 3
Classifier: Programming Language :: Python :: 3.10
Classifier: Programming Language :: Python :: 3.11
Classifier: Programming Language :: Python :: 3.12
Classifier: Programming Language :: Python :: 3.13
Classifier: Programming Language :: Python :: 3.14
Classifier: Operating System :: MacOS
Classifier: Operating System :: POSIX :: Linux
Classifier: License :: OSI Approved :: MIT License
Classifier: Development Status :: 4 - Beta
Classifier: Intended Audience :: Developers
Classifier: Intended Audience :: Financial and Insurance Industry
Classifier: Topic :: Office/Business :: Financial :: Accounting
Requires-Python: >=3.10
License-File: LICENSE.txt
Requires-Dist: polars>=1.0
Requires-Dist: pydantic>=2
Requires-Dist: python-dotenv
Provides-Extra: dev
Requires-Dist: hypothesis; extra == "dev"
Requires-Dist: pytest>=7.0; extra == "dev"
Requires-Dist: pytest-cov; extra == "dev"
Requires-Dist: ruff>=0.2.0; extra == "dev"
Requires-Dist: pre-commit; extra == "dev"
Provides-Extra: graph-dev
Requires-Dist: maturin>=1.0; extra == "graph-dev"
Provides-Extra: jupyter
Requires-Dist: jupyter; extra == "jupyter"
Requires-Dist: seaborn; extra == "jupyter"
Requires-Dist: pyarrow; extra == "jupyter"
Requires-Dist: ipykernel; extra == "jupyter"
Dynamic: license-file
